api_reflector/__init__.py
api_reflector/actions.py
api_reflector/admin.py
api_reflector/api.py
api_reflector/auth.py
api_reflector/db.py
api_reflector/endpoint.py
api_reflector/migrations/README
api_reflector/migrations/__init__.py
api_reflector/migrations/alembic.ini
api_reflector/migrations/env.py
api_reflector/migrations/run_migrations.py
api_reflector/migrations/script.py.mako
api_reflector/migrations/versions/76feeb81949a_callback_action.py
api_reflector/migrations/versions/7b4efa0dd5ea_initial.py
api_reflector/migrations/versions/bf9a283876e7_.py
api_reflector/migrations/versions/d42bddfac4f1_.py
api_reflector/models.py
api_reflector/reporting.py
api_reflector/rules_engine.py
api_reflector/static/bootstrap.min.css
api_reflector/static/filter.js
api_reflector/storage.py
api_reflector/templates/admin/index.html
api_reflector/templates/home.html
api_reflector/templating.py
api_reflector/views.py
settings.py
api_reflector-0.8.4.dist-info/LICENSE
api_reflector-0.8.4.dist-info/METADATA
api_reflector-0.8.4.dist-info/WHEEL
api_reflector-0.8.4.dist-info/entry_points.txt
api_reflector-0.8.4.dist-info/RECORD
