Metadata-Version: 2.1
Name: api-reflector
Version: 0.8.4
Summary: A configurable API mocking service
License: MIT
Author: Chris Latham
Author-email: cl@bink.com
Requires-Python: >=3.9,<4.0
Classifier: License :: OSI Approved :: MIT License
Classifier: Programming Language :: Python :: 3
Classifier: Programming Language :: Python :: 3.9
Classifier: Programming Language :: Python :: 3.10
Classifier: Programming Language :: Python :: 3.11
Classifier: Programming Language :: Python :: 3.12
Requires-Dist: Flask (>=2.2.2,<3.0.0)
Requires-Dist: Flask-Admin (>=1.6.0,<2.0.0)
Requires-Dist: Flask-Cors (>=3.0.10,<4.0.0)
Requires-Dist: Flask-Dance (>=6.1.1,<7.0.0)
Requires-Dist: Flask-SQLAlchemy (>=2.5.1,<3.0.0)
Requires-Dist: Jinja2 (>=3.1.2,<4.0.0)
Requires-Dist: SQLAlchemy (<2)
Requires-Dist: alembic (>=1.8.1,<2.0.0)
Requires-Dist: blinker (>=1.5,<2.0)
Requires-Dist: cachetools (>=5.2.0,<6.0.0)
Requires-Dist: fasteners (>=0.18,<0.19)
Requires-Dist: gunicorn (>=20.1.0,<21.0.0)
Requires-Dist: pendulum (>=2.1.2,<3.0.0)
Requires-Dist: psycopg2-binary (>=2.9.3,<3.0.0)
Requires-Dist: pydantic (>=1.10.2,<2.0.0)
Requires-Dist: python-slugify (>=6.1.2,<7.0.0)
Requires-Dist: sentry-sdk (>=1.9.9,<2.0.0)
Requires-Dist: wtforms (==2.3.3)
